DiskProfiler/__init__.py
DiskProfiler/diskprofiler.py
DiskProfiler-0.4.dist-info/LICENSE
DiskProfiler-0.4.dist-info/METADATA
DiskProfiler-0.4.dist-info/WHEEL
DiskProfiler-0.4.dist-info/top_level.txt
DiskProfiler-0.4.dist-info/RECORD
