Metadata-Version: 2.1
Name: DiskProfiler
Version: 0.4
Summary: Tool for collapsing protoplanetary disk images or spectral cubes into deprojected radially- or azimuthally-averaged profiles.
Home-page: https://github.com/richardseifert/DiskProfiler
Author: Richard Seifert
Author-email: seifertricharda@gmail.com
License: MIT
Platform: UNKNOWN
Requires-Dist: matplotlib
Requires-Dist: numpy
Requires-Dist: scipy
Requires-Dist: astropy
